{"end":"peafowl","path":["unfashionable"],"lookups":{"dowdy":{"valid":true,"relation":"RelatedTo","connectedFrom":"unfashionable","connectFromIndex":0,"connections":[{"connectFromIndex":0,"connectedFrom":"unfashionable","relation":"RelatedTo","hopsToEnd":4,"previousHopsToEnd":5,"proximity":"closer"}],"hopsToEnd":4,"previousHopsToEnd":5,"proximity":"closer"},"dump":{"valid":true,"relation":"RelatedTo","connectedFrom":"unfashionable","connectFromIndex":0,"connections":[{"connectFromIndex":0,"connectedFrom":"unfashionable","relation":"RelatedTo","hopsToEnd":4,"previousHopsToEnd":5,"proximity":"closer"}],"hopsToEnd":4,"previousHopsToEnd":5,"proximity":"closer"},"fashionable":{"valid":true,"relation":"RelatedTo","connectedFrom":"unfashionable","connectFromIndex":0,"connections":[{"connectFromIndex":0,"connectedFrom":"unfashionable","relation":"RelatedTo","hopsToEnd":4,"previousHopsToEnd":5,"proximity":"closer"}],"hopsToEnd":4,"previousHopsToEnd":5,"proximity":"closer"},"loser":{"valid":true,"relation":"RelatedTo","connectedFrom":"unfashionable","connectFromIndex":0,"connections":[{"connectFromIndex":0,"connectedFrom":"unfashionable","relation":"RelatedTo","hopsToEnd":4,"previousHopsToEnd":5,"proximity":"closer"}],"hopsToEnd":4,"previousHopsToEnd":5,"proximity":"closer"},"old":{"valid":true,"relation":"RelatedTo","connectedFrom":"unfashionable","connectFromIndex":0,"connections":[{"connectFromIndex":0,"connectedFrom":"unfashionable","relation":"RelatedTo","hopsToEnd":4,"previousHopsToEnd":5,"proximity":"closer"}],"hopsToEnd":4,"previousHopsToEnd":5,"proximity":"closer"},"out":{"valid":true,"relation":"SimilarTo","connectedFrom":"unfashionable","connectFromIndex":0,"connections":[{"connectFromIndex":0,"connectedFrom":"unfashionable","relation":"SimilarTo","hopsToEnd":4,"previousHopsToEnd":5,"proximity":"closer"}],"hopsToEnd":4,"previousHopsToEnd":5,"proximity":"closer"},"prehistoric":{"valid":true,"relation":"SimilarTo","connectedFrom":"unfashionable","connectFromIndex":0,"connections":[{"connectFromIndex":0,"connectedFrom":"unfashionable","relation":"SimilarTo","hopsToEnd":4,"previousHopsToEnd":5,"proximity":"closer"}],"hopsToEnd":4,"previousHopsToEnd":5,"proximity":"closer"},"sad":{"valid":true,"relation":"RelatedTo","connectedFrom":"unfashionable","connectFromIndex":0,"connections":[{"connectFromIndex":0,"connectedFrom":"unfashionable","relation":"RelatedTo","hopsToEnd":4,"previousHopsToEnd":5,"proximity":"closer"}],"hopsToEnd":4,"previousHopsToEnd":5,"proximity":"closer"}}}
