{"end":"quinquagenarian","path":["sturdy"],"lookups":{"blockhouse":{"valid":true,"relation":"RelatedTo","connectedFrom":"sturdy","connectFromIndex":0,"connections":[{"connectFromIndex":0,"connectedFrom":"sturdy","relation":"RelatedTo","hopsToEnd":4,"previousHopsToEnd":5,"proximity":"closer"}],"hopsToEnd":4,"previousHopsToEnd":5,"proximity":"closer"},"concrete":{"valid":true,"relation":"HasProperty","connectedFrom":"sturdy","connectFromIndex":0,"connections":[{"connectFromIndex":0,"connectedFrom":"sturdy","relation":"HasProperty","hopsToEnd":4,"previousHopsToEnd":5,"proximity":"closer"}],"hopsToEnd":4,"previousHopsToEnd":5,"proximity":"closer"},"disease":{"valid":true,"relation":"RelatedTo","connectedFrom":"sturdy","connectFromIndex":0,"connections":[{"connectFromIndex":0,"connectedFrom":"sturdy","relation":"RelatedTo","hopsToEnd":4,"previousHopsToEnd":5,"proximity":"closer"}],"hopsToEnd":4,"previousHopsToEnd":5,"proximity":"closer"},"dullness":{"valid":true,"relation":"RelatedTo","connectedFrom":"sturdy","connectFromIndex":0,"connections":[{"connectFromIndex":0,"connectedFrom":"sturdy","relation":"RelatedTo","hopsToEnd":4,"previousHopsToEnd":5,"proximity":"closer"}],"hopsToEnd":4,"previousHopsToEnd":5,"proximity":"closer"},"firm":{"valid":true,"relation":"RelatedTo","connectedFrom":"sturdy","connectFromIndex":0,"connections":[{"connectFromIndex":0,"connectedFrom":"sturdy","relation":"RelatedTo","hopsToEnd":4,"previousHopsToEnd":5,"proximity":"closer"}],"hopsToEnd":4,"previousHopsToEnd":5,"proximity":"closer"},"hardy":{"valid":true,"relation":"Synonym","connectedFrom":"sturdy","connectFromIndex":0,"connections":[{"connectFromIndex":0,"connectedFrom":"sturdy","relation":"Synonym","hopsToEnd":4,"previousHopsToEnd":5,"proximity":"closer"}],"hopsToEnd":4,"previousHopsToEnd":5,"proximity":"closer"},"rickety":{"valid":true,"relation":"RelatedTo","connectedFrom":"sturdy","connectFromIndex":0,"connections":[{"connectFromIndex":0,"connectedFrom":"sturdy","relation":"RelatedTo","hopsToEnd":5,"previousHopsToEnd":5,"proximity":"same"}],"hopsToEnd":5,"previousHopsToEnd":5,"proximity":"same"},"rugged":{"valid":true,"relation":"SimilarTo","connectedFrom":"sturdy","connectFromIndex":0,"connections":[{"connectFromIndex":0,"connectedFrom":"sturdy","relation":"SimilarTo","hopsToEnd":5,"previousHopsToEnd":5,"proximity":"same"}],"hopsToEnd":5,"previousHopsToEnd":5,"proximity":"same"},"stour":{"valid":true,"relation":"RelatedTo","connectedFrom":"sturdy","connectFromIndex":0,"connections":[{"connectFromIndex":0,"connectedFrom":"sturdy","relation":"RelatedTo","hopsToEnd":4,"previousHopsToEnd":5,"proximity":"closer"}],"hopsToEnd":4,"previousHopsToEnd":5,"proximity":"closer"},"structure":{"valid":true,"relation":"RelatedTo","connectedFrom":"sturdy","connectFromIndex":0,"connections":[{"connectFromIndex":0,"connectedFrom":"sturdy","relation":"RelatedTo","hopsToEnd":4,"previousHopsToEnd":5,"proximity":"closer"}],"hopsToEnd":4,"previousHopsToEnd":5,"proximity":"closer"},"stupor":{"valid":true,"relation":"RelatedTo","connectedFrom":"sturdy","connectFromIndex":0,"connections":[{"connectFromIndex":0,"connectedFrom":"sturdy","relation":"RelatedTo","hopsToEnd":4,"previousHopsToEnd":5,"proximity":"closer"}],"hopsToEnd":4,"previousHopsToEnd":5,"proximity":"closer"},"tapeworm":{"valid":true,"relation":"RelatedTo","connectedFrom":"sturdy","connectFromIndex":0,"connections":[{"connectFromIndex":0,"connectedFrom":"sturdy","relation":"RelatedTo","hopsToEnd":4,"previousHopsToEnd":5,"proximity":"closer"}],"hopsToEnd":4,"previousHopsToEnd":5,"proximity":"closer"},"tough":{"valid":true,"relation":"Synonym","connectedFrom":"sturdy","connectFromIndex":0,"connections":[{"connectFromIndex":0,"connectedFrom":"sturdy","relation":"Synonym","hopsToEnd":4,"previousHopsToEnd":5,"proximity":"closer"}],"hopsToEnd":4,"previousHopsToEnd":5,"proximity":"closer"},"workbench":{"valid":true,"relation":"RelatedTo","connectedFrom":"sturdy","connectFromIndex":0,"connections":[{"connectFromIndex":0,"connectedFrom":"sturdy","relation":"RelatedTo","hopsToEnd":4,"previousHopsToEnd":5,"proximity":"closer"}],"hopsToEnd":4,"previousHopsToEnd":5,"proximity":"closer"}}}
